marklidenberg_donyfiles/__init__.py
marklidenberg_donyfiles/release.py
marklidenberg_donyfiles/split_merge.py
marklidenberg_donyfiles/squash.py
marklidenberg_donyfiles/update_secrets_baseline.py
marklidenberg_donyfiles-0.4.0.dist-info/METADATA
marklidenberg_donyfiles-0.4.0.dist-info/WHEEL
marklidenberg_donyfiles-0.4.0.dist-info/licenses/LICENSE
marklidenberg_donyfiles-0.4.0.dist-info/RECORD
